AUTHORS
LICENSE
MANIFEST.in
README.rst
setup.py
docs/Makefile
docs/conf.py
docs/index.rst
docs/make.bat
pychex/__init__.py
pychex/cli.py
pychex/exceptions.py
pychex/paychex.py
pychex.egg-info/PKG-INFO
pychex.egg-info/SOURCES.txt
pychex.egg-info/dependency_links.txt
pychex.egg-info/entry_points.txt
pychex.egg-info/requires.txt
pychex.egg-info/top_level.txt
pychex/templates/GetUserApplicationAccountData.soap.xml
requirements/base.txt
requirements/dev.txt
requirements/test.txt